proctoru/models.py
proctoru/__init__.py
proctoru/api.py
proctoru/admin.py
proctoru/timezonemap.py
proctoru/proctoru.py
proctoru/templatetags/proctoru_validator.py
proctoru/templatetags/__init__.py
proctoru/public/css/custom_bootstrap.css
proctoru/public/css/proctoru.css
proctoru/public/images/arrow.png
proctoru/public/images/loader.gif
proctoru/public/images/right-arrow.png
proctoru/public/images/checked.png
proctoru/public/images/left-arrow.png
proctoru/public/images/owl.png
proctoru/static/README.txt
proctoru/static/js/src/lms_view.js
proctoru/static/js/src/studio_edit.js
proctoru/static/js/src/proctoru.js
proctoru/static/html/staff-view.html
proctoru/static/html/shedule_form_proctoru.html
proctoru/static/html/exam_ended.html
proctoru/static/html/exam_enabled.html
proctoru/static/html/blank.html
proctoru/static/html/exam_completed.html
proctoru/static/html/reshedule_form_proctoru.html
proctoru/static/html/error_template.html
proctoru/static/html/studio.html
proctoru/static/html/proctoru.html
proctoru/static/html/sequence.html
proctoru/static/html/exam_arrived_proctoru.html
proctoru/static/html/exam_password.html
proctoru/static/html/studio_edit.html
proctoru_xblock-1.0.0.dist-info/METADATA
proctoru_xblock-1.0.0.dist-info/top_level.txt
proctoru_xblock-1.0.0.dist-info/metadata.json
proctoru_xblock-1.0.0.dist-info/WHEEL
proctoru_xblock-1.0.0.dist-info/RECORD
proctoru_xblock-1.0.0.dist-info/entry_points.txt
proctoru_xblock-1.0.0.dist-info/DESCRIPTION.rst
