Metadata-Version: 2.0
Name: proctoru-xblock
Version: 1.0.0
Summary: ProctorU is an online proctoring company that allows a candidate to take their exam from home
Home-page: UNKNOWN
Author: UNKNOWN
Author-email: UNKNOWN
License: UNKNOWN
Platform: UNKNOWN
Requires-Dist: XBlock
